galatasaray/__init__.py
galatasaray/__main__.py
galatasaray/cli.py
galatasaray/scrapper.py
galatasaray/screen.py
galatasaray-0.1.8.dist-info/LICENSE.txt
galatasaray-0.1.8.dist-info/METADATA
galatasaray-0.1.8.dist-info/WHEEL
galatasaray-0.1.8.dist-info/entry_points.txt
galatasaray-0.1.8.dist-info/RECORD
